typing_validation/__init__.py
typing_validation/inspector.py
typing_validation/py.typed
typing_validation/validation.py
typing_validation/validation_failure.py
typing_validation-1.2.11.post4.dist-info/LICENSE
typing_validation-1.2.11.post4.dist-info/METADATA
typing_validation-1.2.11.post4.dist-info/WHEEL
typing_validation-1.2.11.post4.dist-info/top_level.txt
typing_validation-1.2.11.post4.dist-info/RECORD
